deepclient/__init__.py
deepclient/deep_client.py
deepclient/deep_client_options.py
deepclient/query.py
deepclient/generate_gql_operations/__init__.py
deepclient/generate_gql_operations/mutation.py
deepclient/generate_gql_operations/serial.py
tests/__init__.py
tests/test_deep_client.py
deepclient_test-1.0.5.dist-info/METADATA
deepclient_test-1.0.5.dist-info/WHEEL
deepclient_test-1.0.5.dist-info/top_level.txt
deepclient_test-1.0.5.dist-info/RECORD
