Metadata-Version: 2.1
Name: deepclient-test
Version: 1.0.5
Summary: Deep Client - a way to connect your favorite language with Deep
Home-page: https://github.com/Lotos2021/deepclient-test
License: Unlicense
Classifier: Development Status :: 3 - Alpha
Classifier: License :: OSI Approved :: The Unlicense (Unlicense)
Classifier: Programming Language :: Python
Classifier: Programming Language :: Python :: 3
Classifier: Programming Language :: Python :: 3.6
Classifier: Programming Language :: Python :: 3.7
Classifier: Programming Language :: Python :: 3.8
Classifier: Programming Language :: Python :: 3.9
Classifier: Programming Language :: Python :: 3.10
Requires-Dist: aiohttp (==3.8.4)
Requires-Dist: aiosignal (==1.3.1)
Requires-Dist: async-timeout (==4.0.2)
Requires-Dist: backoff (==2.2.1)
Requires-Dist: botocore (==1.29.129)
Requires-Dist: frozenlist (==1.3.3)
Requires-Dist: gql (==3.4.1)
Requires-Dist: graphql-core (==3.2.3)
Requires-Dist: jmespath (==1.0.1)
Requires-Dist: multidict (==6.0.4)
Requires-Dist: websockets (==10.4)
Requires-Dist: yarl (==1.9.2)
